<?xml version="1.0" encoding="UTF-8"?>
<annotation>
	<folder>data</folder>
	<filename>0187</filename>
	<path>data/0187</path>
	<source>
		<database>Unknown</database>
	</source>
	<size>
		<width>384</width>
		<height>288</height>
		<depth>3</depth>
	</size>
	<segmented>0</segmented>
	<object>
		<name>person</name>
		<pose>Unspecified</pose>
		<truncated>0</truncated>
		<difficult>0</difficult>
		<bndbox>
			<xmin>267</xmin>
			<ymin>40</ymin>
			<xmax>279</xmax>
			<ymax>73</ymax>
		</bndbox>
	</object>
	<object>
		<name>person</name>
		<pose>Unspecified</pose>
		<truncated>0</truncated>
		<difficult>0</difficult>
		<bndbox>
			<xmin>165</xmin>
			<ymin>62</ymin>
			<xmax>180</xmax>
			<ymax>100</ymax>
		</bndbox>
	</object>
	<object>
		<name>person</name>
		<pose>Unspecified</pose>
		<truncated>0</truncated>
		<difficult>0</difficult>
		<bndbox>
			<xmin>224</xmin>
			<ymin>52</ymin>
			<xmax>237</xmax>
			<ymax>86</ymax>
		</bndbox>
	</object>
</annotation>
