<?xml version="1.0" encoding="UTF-8"?>
<annotation>
	<folder>data</folder>
	<filename>0915</filename>
	<path>data/0915</path>
	<source>
		<database>Unknown</database>
	</source>
	<size>
		<width>640</width>
		<height>512</height>
		<depth>3</depth>
	</size>
	<segmented>0</segmented>
	<object>
		<name>person</name>
		<pose>Unspecified</pose>
		<truncated>0</truncated>
		<difficult>0</difficult>
		<bndbox>
			<xmin>324</xmin>
			<ymin>198</ymin>
			<xmax>343</xmax>
			<ymax>257</ymax>
		</bndbox>
	</object>
	<object>
		<name>person</name>
		<pose>Unspecified</pose>
		<truncated>0</truncated>
		<difficult>0</difficult>
		<bndbox>
			<xmin>524</xmin>
			<ymin>78</ymin>
			<xmax>538</xmax>
			<ymax>116</ymax>
		</bndbox>
	</object>
	<object>
		<name>person</name>
		<pose>Unspecified</pose>
		<truncated>0</truncated>
		<difficult>0</difficult>
		<bndbox>
			<xmin>94</xmin>
			<ymin>269</ymin>
			<xmax>117</xmax>
			<ymax>332</ymax>
		</bndbox>
	</object>
	<object>
		<name>person</name>
		<pose>Unspecified</pose>
		<truncated>0</truncated>
		<difficult>0</difficult>
		<bndbox>
			<xmin>349</xmin>
			<ymin>201</ymin>
			<xmax>367</xmax>
			<ymax>237</ymax>
		</bndbox>
	</object>
</annotation>
