<annotation>
	<folder>JPEGImages</folder>
	<filename>7 (165).jpg</filename>
	<path>C:\Users\赵文龙\Desktop\VOC2007\JPEGImages\7 (165).jpg</path>
	<source>
		<database>Unknown</database>
	</source>
	<size>
		<width>2924</width>
		<height>2924</height>
		<depth>3</depth>
	</size>
	<segmented>0</segmented>
	<object>
		<name>Shockproof hammer</name>
		<pose>Unspecified</pose>
		<truncated>0</truncated>
		<difficult>0</difficult>
		<bndbox>
			<xmin>948</xmin>
			<ymin>1280</ymin>
			<xmax>1536</xmax>
			<ymax>1772</ymax>
		</bndbox>
	</object>
</annotation>
