<annotation>
	<folder>JPEGImages</folder>
	<filename>8 (260).jpg</filename>
	<path>C:\Users\赵文龙\Desktop\VOC2007\JPEGImages\8 (260).jpg</path>
	<source>
		<database>Unknown</database>
	</source>
	<size>
		<width>1289</width>
		<height>1289</height>
		<depth>3</depth>
	</size>
	<segmented>0</segmented>
	<object>
		<name>Damage of shockproof hammer</name>
		<pose>Unspecified</pose>
		<truncated>0</truncated>
		<difficult>0</difficult>
		<bndbox>
			<xmin>678</xmin>
			<ymin>631</ymin>
			<xmax>1020</xmax>
			<ymax>914</ymax>
		</bndbox>
	</object>
</annotation>
