<annotation>
	<folder>JPEGImages</folder>
	<filename>3 (364).jpg</filename>
	<path>C:\Users\赵文龙\Desktop\VOC2007\JPEGImages\3 (364).jpg</path>
	<source>
		<database>Unknown</database>
	</source>
	<size>
		<width>2325</width>
		<height>2160</height>
		<depth>1</depth>
	</size>
	<segmented>0</segmented>
	<object>
		<name>wire foreign body</name>
		<pose>Unspecified</pose>
		<truncated>0</truncated>
		<difficult>0</difficult>
		<bndbox>
			<xmin>640</xmin>
			<ymin>581</ymin>
			<xmax>2060</xmax>
			<ymax>1717</ymax>
		</bndbox>
	</object>
</annotation>
