<annotation>
	<folder>JPEGImages</folder>
	<filename>4 (432).jpg</filename>
	<path>C:\Users\赵文龙\Desktop\VOC2007\JPEGImages\4 (432).jpg</path>
	<source>
		<database>Unknown</database>
	</source>
	<size>
		<width>3212</width>
		<height>3212</height>
		<depth>3</depth>
	</size>
	<segmented>0</segmented>
	<object>
		<name>insulator missing</name>
		<pose>Unspecified</pose>
		<truncated>0</truncated>
		<difficult>0</difficult>
		<bndbox>
			<xmin>1364</xmin>
			<ymin>1538</ymin>
			<xmax>1795</xmax>
			<ymax>1977</ymax>
		</bndbox>
	</object>
</annotation>
