<annotation>
	<folder>JPEGImages</folder>
	<filename>1 (225).jpg</filename>
	<path>C:\Users\赵文龙\Desktop\VOC2007\JPEGImages\1 (225).jpg</path>
	<source>
		<database>Unknown</database>
	</source>
	<size>
		<width>4766</width>
		<height>4766</height>
		<depth>3</depth>
	</size>
	<segmented>0</segmented>
	<object>
		<name>niaowo</name>
		<pose>Unspecified</pose>
		<truncated>0</truncated>
		<difficult>0</difficult>
		<bndbox>
			<xmin>1652</xmin>
			<ymin>2259</ymin>
			<xmax>2612</xmax>
			<ymax>3199</ymax>
		</bndbox>
	</object>
</annotation>
