<annotation>
	<folder>JPEGImages</folder>
	<filename>6 (170).jpg</filename>
	<path>C:\Users\赵文龙\Desktop\VOC2007\JPEGImages\6 (170).jpg</path>
	<source>
		<database>Unknown</database>
	</source>
	<size>
		<width>2560</width>
		<height>2560</height>
		<depth>3</depth>
	</size>
	<segmented>0</segmented>
	<object>
		<name>Insulator flashover</name>
		<pose>Unspecified</pose>
		<truncated>0</truncated>
		<difficult>0</difficult>
		<bndbox>
			<xmin>292</xmin>
			<ymin>321</ymin>
			<xmax>917</xmax>
			<ymax>924</ymax>
		</bndbox>
	</object>
	<object>
		<name>Insulator flashover</name>
		<pose>Unspecified</pose>
		<truncated>0</truncated>
		<difficult>0</difficult>
		<bndbox>
			<xmin>1531</xmin>
			<ymin>1660</ymin>
			<xmax>2103</xmax>
			<ymax>2206</ymax>
		</bndbox>
	</object>
</annotation>
